[
    {
        "createdAt" : 1772583465.0274,
        "frameNumber" : 0,
        "id" : "AEBE7290-3FE9-44D8-B601-B8DB1CF1124B",
        "name" : "Stand",
        "objects" : [],
        "pose" : {
            "figureOffsetX" : 0,
            "figureOffsetY" : 0,
            "figureScale" : 1,
            "footColor" : "#000000",
            "footSize" : 1,
            "fusiformLowerArms" : 2,
            "fusiformLowerLegs" : 2.48,
            "fusiformLowerTorso" : 1,
            "fusiformShoulders" : 1.52,
            "fusiformUpperArms" : 2.74,
            "fusiformUpperLegs" : 2.95,
            "fusiformUpperTorso" : 5.85,
            "handColor" : "#000000",
            "handSize" : 1,
            "headAngle" : 0,
            "headColor" : "#000000",
            "headRadiusMultiplier" : 1,
            "jointColor" : "#000000",
            "jointShapeSize" : 1,
            "leftArmColor" : "#000000",
            "leftElbowAngle" : -26,
            "leftFootAngle" : 0,
            "leftHandAngle" : 0,
            "leftHipAngle" : 0,
            "leftKneeAngle" : -166,
            "leftLegColor" : "#000000",
            "leftLowerArmColor" : "#000000",
            "leftLowerLegColor" : "#000000",
            "leftShoulderAngle" : -147,
            "leftUpperArmColor" : "#000000",
            "leftUpperLegColor" : "#000000",
            "midTorsoAngle" : 0,
            "neckLength" : 21,
            "neckWidth" : 8.5,
            "peakPositionLowerArms" : 0.3,
            "peakPositionLowerLegs" : 0.2,
            "peakPositionLowerTorso" : 0.5,
            "peakPositionUpperArms" : 0.47,
            "peakPositionUpperLegs" : 0.2,
            "peakPositionUpperTorso" : 0.1,
            "rightArmColor" : "#000000",
            "rightElbowAngle" : 26,
            "rightFootAngle" : 0,
            "rightHandAngle" : 0,
            "rightHipAngle" : 0,
            "rightKneeAngle" : 167,
            "rightLegColor" : "#000000",
            "rightLowerArmColor" : "#000000",
            "rightLowerLegColor" : "#000000",
            "rightShoulderAngle" : 147,
            "rightUpperArmColor" : "#000000",
            "rightUpperLegColor" : "#000000",
            "scale" : 1,
            "shoulderWidthMultiplier" : 0.52,
            "skeletonSize" : 4.18,
            "strokeThickness" : 1.2,
            "strokeThicknessJoints" : 2,
            "strokeThicknessLowerArms" : 4,
            "strokeThicknessLowerLegs" : 4,
            "strokeThicknessLowerTorso" : 5,
            "strokeThicknessMultiplier" : 1.2,
            "strokeThicknessUpperArms" : 4,
            "strokeThicknessUpperLegs" : 5,
            "strokeThicknessUpperTorso" : 5,
            "torsoColor" : "#000000",
            "torsoRotationAngle" : 0,
            "waistPositionX" : 300,
            "waistPositionY" : 360,
            "waistThicknessMultiplier" : 0.9,
            "waistTorsoAngle" : 0,
            "waistWidthMultiplier" : 0.26
        }
    },
  {
    "createdAt" : 1772655562.719,
    "frameNumber" : 0,
    "id" : "4D5AD764-7614-41AC-9091-DC55DD3510EA",
    "name" : "Large Stand",
    "objects" : [
    ],
    "pose" : {
      "figureOffsetX" : 0,
      "figureOffsetY" : 0,
      "figureScale" : 1,
      "footColor" : "#000000",
      "footSize" : 7,
      "fusiformLowerArms" : 2.74,
      "fusiformLowerLegs" : 3.15,
      "fusiformLowerTorso" : 0,
      "fusiformShoulders" : 1.81,
      "fusiformUpperArms" : 3.17,
      "fusiformUpperLegs" : 3.18,
      "fusiformUpperTorso" : 5.82,
      "handColor" : "#000000",
      "handSize" : 7,
      "headAngle" : 0,
      "headColor" : "#000000",
      "headRadiusMultiplier" : 1,
      "jointColor" : "#000000",
      "jointShapeSize" : 1,
      "leftArmColor" : "#000000",
      "leftElbowAngle" : -26,
      "leftFootAngle" : 0,
      "leftHandAngle" : 0,
      "leftHipAngle" : 0,
      "leftKneeAngle" : -167,
      "leftLegColor" : "#000000",
      "leftLowerArmColor" : "#000000",
      "leftLowerLegColor" : "#000000",
      "leftShoulderAngle" : -144,
      "leftUpperArmColor" : "#000000",
      "leftUpperLegColor" : "#000000",
      "midTorsoAngle" : 0,
      "neckLength" : 21,
      "neckWidth" : 8.8,
      "peakPositionLowerArms" : 0.3,
      "peakPositionLowerLegs" : 0.34,
      "peakPositionLowerTorso" : 0.1,
      "peakPositionUpperArms" : 0.48,
      "peakPositionUpperLegs" : 0.37,
      "peakPositionUpperTorso" : 0.1,
      "rightArmColor" : "#000000",
      "rightElbowAngle" : 26,
      "rightFootAngle" : 0,
      "rightHandAngle" : 0,
      "rightHipAngle" : 0,
      "rightKneeAngle" : 167,
      "rightLegColor" : "#000000",
      "rightLowerArmColor" : "#000000",
      "rightLowerLegColor" : "#000000",
      "rightShoulderAngle" : 144,
      "rightUpperArmColor" : "#000000",
      "rightUpperLegColor" : "#000000",
      "scale" : 1,
      "shoulderWidthMultiplier" : 0.52,
      "skeletonSize" : 5.11,
      "strokeThickness" : 1.4,
      "strokeThicknessJoints" : 2,
      "strokeThicknessLowerArms" : 4,
      "strokeThicknessLowerLegs" : 4,
      "strokeThicknessLowerTorso" : 5,
      "strokeThicknessMultiplier" : 1.4,
      "strokeThicknessUpperArms" : 4,
      "strokeThicknessUpperLegs" : 5,
      "strokeThicknessUpperTorso" : 5,
      "torsoColor" : "#000000",
      "torsoRotationAngle" : 0,
      "waistPositionX" : 300,
      "waistPositionY" : 360,
      "waistThicknessMultiplier" : 0.9,
      "waistTorsoAngle" : 0,
      "waistWidthMultiplier" : 0.28
    }
  },
  {
    "createdAt" : 1772655896.9752,
    "frameNumber" : 0,
    "id" : "D3130455-2AEB-4E5B-8A27-2A6857917D6C",
    "name" : "Extra Large Stand",
    "objects" : [
    ],
    "pose" : {
      "figureOffsetX" : 0,
      "figureOffsetY" : 0,
      "figureScale" : 1,
      "footColor" : "#000000",
      "footSize" : 7,
      "fusiformLowerArms" : 2.74,
      "fusiformLowerLegs" : 2.95,
      "fusiformLowerTorso" : 0,
      "fusiformShoulders" : 1.81,
      "fusiformUpperArms" : 3.17,
      "fusiformUpperLegs" : 2.68,
      "fusiformUpperTorso" : 5.82,
      "handColor" : "#000000",
      "handSize" : 7,
      "headAngle" : 0,
      "headColor" : "#000000",
      "headRadiusMultiplier" : 1,
      "jointColor" : "#000000",
      "jointShapeSize" : 1,
      "leftArmColor" : "#000000",
      "leftElbowAngle" : -26,
      "leftFootAngle" : 0,
      "leftHandAngle" : 0,
      "leftHipAngle" : 0,
      "leftKneeAngle" : -167,
      "leftLegColor" : "#000000",
      "leftLowerArmColor" : "#000000",
      "leftLowerLegColor" : "#000000",
      "leftShoulderAngle" : -144,
      "leftUpperArmColor" : "#000000",
      "leftUpperLegColor" : "#000000",
      "midTorsoAngle" : 0,
      "neckLength" : 21,
      "neckWidth" : 8.8,
      "peakPositionLowerArms" : 0.3,
      "peakPositionLowerLegs" : 0.34,
      "peakPositionLowerTorso" : 0.1,
      "peakPositionUpperArms" : 0.48,
      "peakPositionUpperLegs" : 0.37,
      "peakPositionUpperTorso" : 0.1,
      "rightArmColor" : "#000000",
      "rightElbowAngle" : 26,
      "rightFootAngle" : 0,
      "rightHandAngle" : 0,
      "rightHipAngle" : 0,
      "rightKneeAngle" : 167,
      "rightLegColor" : "#000000",
      "rightLowerArmColor" : "#000000",
      "rightLowerLegColor" : "#000000",
      "rightShoulderAngle" : 144,
      "rightUpperArmColor" : "#000000",
      "rightUpperLegColor" : "#000000",
      "scale" : 1,
      "shoulderWidthMultiplier" : 0.52,
      "skeletonSize" : 5.11,
      "strokeThickness" : 2,
      "strokeThicknessJoints" : 2,
      "strokeThicknessLowerArms" : 4,
      "strokeThicknessLowerLegs" : 4,
      "strokeThicknessLowerTorso" : 5,
      "strokeThicknessMultiplier" : 2,
      "strokeThicknessUpperArms" : 4,
      "strokeThicknessUpperLegs" : 5,
      "strokeThicknessUpperTorso" : 5,
      "torsoColor" : "#000000",
      "torsoRotationAngle" : 0,
      "waistPositionX" : 300,
      "waistPositionY" : 360,
      "waistThicknessMultiplier" : 0.9,
      "waistTorsoAngle" : 0,
      "waistWidthMultiplier" : 0.28
    }
  },
    {
      "createdAt" : 1772656481.6926,
      "frameNumber" : 0,
      "id" : "EC011614-9883-4704-891D-A0662164DAED",
      "name" : "Extra Small Stand",
      "objects" : [
      ],
      "pose" : {
        "figureOffsetX" : 0,
        "figureOffsetY" : 0,
        "figureScale" : 1,
        "footColor" : "#000000",
        "footSize" : 0.5,
        "fusiformLowerArms" : 0,
        "fusiformLowerLegs" : 0,
        "fusiformLowerTorso" : 0,
        "fusiformShoulders" : 0,
        "fusiformUpperArms" : 0,
        "fusiformUpperLegs" : 0,
        "fusiformUpperTorso" : 0,
        "handColor" : "#000000",
        "handSize" : 0.5,
        "headAngle" : 0,
        "headColor" : "#000000",
        "headRadiusMultiplier" : 1,
        "jointColor" : "#000000",
        "jointShapeSize" : 0,
        "leftArmColor" : "#000000",
        "leftElbowAngle" : -26,
        "leftFootAngle" : 0,
        "leftHandAngle" : 0,
        "leftHipAngle" : 0,
        "leftKneeAngle" : -166,
        "leftLegColor" : "#000000",
        "leftLowerArmColor" : "#000000",
        "leftLowerLegColor" : "#000000",
        "leftShoulderAngle" : -147,
        "leftUpperArmColor" : "#000000",
        "leftUpperLegColor" : "#000000",
        "midTorsoAngle" : 0,
        "neckLength" : 21,
        "neckWidth" : 3.3,
        "peakPositionLowerArms" : 0.1,
        "peakPositionLowerLegs" : 0.1,
        "peakPositionLowerTorso" : 0.1,
        "peakPositionUpperArms" : 0.1,
        "peakPositionUpperLegs" : 0.1,
        "peakPositionUpperTorso" : 0.1,
        "rightArmColor" : "#000000",
        "rightElbowAngle" : 26,
        "rightFootAngle" : 0,
        "rightHandAngle" : 0,
        "rightHipAngle" : 0,
        "rightKneeAngle" : 167,
        "rightLegColor" : "#000000",
        "rightLowerArmColor" : "#000000",
        "rightLowerLegColor" : "#000000",
        "rightShoulderAngle" : 147,
        "rightUpperArmColor" : "#000000",
        "rightUpperLegColor" : "#000000",
        "scale" : 1,
        "shoulderWidthMultiplier" : 0.52,
        "skeletonSize" : 0.0,
        "strokeThickness" : 0.0,
        "strokeThicknessJoints" : 2,
        "strokeThicknessLowerArms" : 4,
        "strokeThicknessLowerLegs" : 4,
        "strokeThicknessLowerTorso" : 5,
        "strokeThicknessMultiplier" : 0.5,
        "strokeThicknessUpperArms" : 4,
        "strokeThicknessUpperLegs" : 5,
        "strokeThicknessUpperTorso" : 5,
        "torsoColor" : "#000000",
        "torsoRotationAngle" : 0,
        "waistPositionX" : 300,
        "waistPositionY" : 360,
        "waistThicknessMultiplier" : 0,
        "waistTorsoAngle" : 0,
        "waistWidthMultiplier" : 0.26
      }
    },
  {
    "createdAt" : 1772657999.942,
    "frameNumber" : 0,
    "id" : "DDCDD519-562F-4CD4-B9BB-CFFF6992C0B9",
    "name" : "Small Stand",
    "objects" : [
    ],
    "pose" : {
      "figureOffsetX" : 0,
      "figureOffsetY" : 0,
      "figureScale" : 1,
      "footColor" : "#000000",
      "footSize" : 0.5,
      "fusiformLowerArms" : 1.64,
      "fusiformLowerLegs" : 1.8,
      "fusiformLowerTorso" : 0,
      "fusiformShoulders" : 0.34,
      "fusiformUpperArms" : 2.1,
      "fusiformUpperLegs" : 1.69,
      "fusiformUpperTorso" : 2.18,
      "handColor" : "#000000",
      "handSize" : 0.5,
      "headAngle" : 0,
      "headColor" : "#000000",
      "headRadiusMultiplier" : 1,
      "jointColor" : "#000000",
      "jointShapeSize" : 1,
      "leftArmColor" : "#000000",
      "leftElbowAngle" : -26,
      "leftFootAngle" : 0,
      "leftHandAngle" : 0,
      "leftHipAngle" : 0,
      "leftKneeAngle" : -166,
      "leftLegColor" : "#000000",
      "leftLowerArmColor" : "#000000",
      "leftLowerLegColor" : "#000000",
      "leftShoulderAngle" : -147,
      "leftUpperArmColor" : "#000000",
      "leftUpperLegColor" : "#000000",
      "midTorsoAngle" : 0,
      "neckLength" : 21,
      "neckWidth" : 3.3,
      "peakPositionLowerArms" : 0.1,
      "peakPositionLowerLegs" : 0.1,
      "peakPositionLowerTorso" : 0.1,
      "peakPositionUpperArms" : 0.1,
      "peakPositionUpperLegs" : 0.1,
      "peakPositionUpperTorso" : 0.1,
      "rightArmColor" : "#000000",
      "rightElbowAngle" : 26,
      "rightFootAngle" : 0,
      "rightHandAngle" : 0,
      "rightHipAngle" : 0,
      "rightKneeAngle" : 167,
      "rightLegColor" : "#000000",
      "rightLowerArmColor" : "#000000",
      "rightLowerLegColor" : "#000000",
      "rightShoulderAngle" : 147,
      "rightUpperArmColor" : "#000000",
      "rightUpperLegColor" : "#000000",
      "scale" : 1,
      "shoulderWidthMu0plier" : 0.52,
      "skeletonSize" : 3.19,
      "strokeThickness" : 1,
      "strokeThicknessJoints" : 2,
      "strokeThicknessLowerArms" : 4,
      "strokeThicknessLowerLegs" : 4,
      "strokeThicknessLowerTorso" : 5,
      "strokeThicknessMultiplier" : 1,
      "strokeThicknessUpperArms" : 4,
      "strokeThicknessUpperLegs" : 5,
      "strokeThicknessUpperTorso" : 5,
      "torsoColor" : "#000000",
      "torsoRotationAngle" : 0,
      "waistPositionX" : 300,
      "waistPositionY" : 360,
      "waistThicknessMultiplier" : 0.9,
      "waistTorsoAngle" : 0,
      "waistWidthMultiplier" : 0.26
    }
  },
  {
      "createdAt" : 1772665153.0754,
      "frameNumber" : 1,
      "id" : "D2381280-6CDC-4544-A906-A327AF4E0943",
      "name" : "Move",
      "objects" : [
      ],
      "pose" : {
        "figureOffsetX" : 0,
        "figureOffsetY" : 0,
        "figureScale" : 1,
        "footColor" : "#000000",
        "footSize" : 0.5,
        "fusiformLowerArms" : 0,
        "fusiformLowerLegs" : 0,
        "fusiformLowerTorso" : 0,
        "fusiformShoulders" : 0,
        "fusiformUpperArms" : 0,
        "fusiformUpperLegs" : 0,
        "fusiformUpperTorso" : 0,
        "handColor" : "#000000",
        "handSize" : 0.5,
        "headAngle" : 0,
        "headColor" : "#000000",
        "headRadiusMultiplier" : 1,
        "jointColor" : "#000000",
        "jointShapeSize" : 1,
        "leftArmColor" : "#000000",
        "leftElbowAngle" : -26,
        "leftFootAngle" : 34,
        "leftHandAngle" : 0,
        "leftHipAngle" : 0,
        "leftKneeAngle" : -177,
        "leftLegColor" : "#000000",
        "leftLowerArmColor" : "#000000",
        "leftLowerLegColor" : "#000000",
        "leftShoulderAngle" : -164,
        "leftUpperArmColor" : "#000000",
        "leftUpperLegColor" : "#000000",
        "midTorsoAngle" : 0,
        "neckLength" : 21,
        "neckWidth" : 3.3,
        "peakPositionLowerArms" : 0.1,
        "peakPositionLowerLegs" : 0.1,
        "peakPositionLowerTorso" : 0.1,
        "peakPositionUpperArms" : 0.1,
        "peakPositionUpperLegs" : 0.1,
        "peakPositionUpperTorso" : 0.1,
        "rightArmColor" : "#000000",
        "rightElbowAngle" : -26,
        "rightFootAngle" : 26,
        "rightHandAngle" : 0,
        "rightHipAngle" : 0,
        "rightKneeAngle" : 167,
        "rightLegColor" : "#000000",
        "rightLowerArmColor" : "#000000",
        "rightLowerLegColor" : "#000000",
        "rightShoulderAngle" : 152,
        "rightUpperArmColor" : "#000000",
        "rightUpperLegColor" : "#000000",
        "scale" : 1,
        "shoulderWidthMultiplier" : 0,
        "skeletonSize" : 0.5,
        "strokeThickness" : 0.5,
        "strokeThicknessJoints" : 2,
        "strokeThicknessLowerArms" : 4,
        "strokeThicknessLowerLegs" : 4,
        "strokeThicknessLowerTorso" : 5,
        "strokeThicknessMultiplier" : 0.5,
        "strokeThicknessUpperArms" : 4,
        "strokeThicknessUpperLegs" : 5,
        "strokeThicknessUpperTorso" : 5,
        "torsoColor" : "#000000",
        "torsoRotationAngle" : 0,
        "waistPositionX" : 300,
        "waistPositionY" : 360,
        "waistThicknessMultiplier" : 0,
        "waistTorsoAngle" : 0,
        "waistWidthMultiplier" : 0
      }
    },
  {
    "createdAt" : 1772665176.1086,
    "frameNumber" : 2,
    "id" : "D557F64B-5059-465F-ACB3-5EBD56614674",
    "name" : "Move",
    "objects" : [
    ],
    "pose" : {
      "figureOffsetX" : 0,
      "figureOffsetY" : 0,
      "figureScale" : 1,
      "footColor" : "#000000",
      "footSize" : 0.5,
      "fusiformLowerArms" : 0,
      "fusiformLowerLegs" : 0,
      "fusiformLowerTorso" : 0,
      "fusiformShoulders" : 0,
      "fusiformUpperArms" : 0,
      "fusiformUpperLegs" : 0,
      "fusiformUpperTorso" : 0,
      "handColor" : "#000000",
      "handSize" : 0.5,
      "headAngle" : 0,
      "headColor" : "#000000",
      "headRadiusMultiplier" : 1,
      "jointColor" : "#000000",
      "jointShapeSize" : 1,
      "leftArmColor" : "#000000",
      "leftElbowAngle" : -26,
      "leftFootAngle" : 34,
      "leftHandAngle" : 0,
      "leftHipAngle" : 0,
      "leftKneeAngle" : -191,
      "leftLegColor" : "#000000",
      "leftLowerArmColor" : "#000000",
      "leftLowerLegColor" : "#000000",
      "leftShoulderAngle" : -186,
      "leftUpperArmColor" : "#000000",
      "leftUpperLegColor" : "#000000",
      "midTorsoAngle" : 0,
      "neckLength" : 21,
      "neckWidth" : 3.3,
      "peakPositionLowerArms" : 0.1,
      "peakPositionLowerLegs" : 0.1,
      "peakPositionLowerTorso" : 0.1,
      "peakPositionUpperArms" : 0.1,
      "peakPositionUpperLegs" : 0.1,
      "peakPositionUpperTorso" : 0.1,
      "rightArmColor" : "#000000",
      "rightElbowAngle" : -26,
      "rightFootAngle" : 82,
      "rightHandAngle" : 0,
      "rightHipAngle" : 0,
      "rightKneeAngle" : 167,
      "rightLegColor" : "#000000",
      "rightLowerArmColor" : "#000000",
      "rightLowerLegColor" : "#000000",
      "rightShoulderAngle" : 194,
      "rightUpperArmColor" : "#000000",
      "rightUpperLegColor" : "#000000",
      "scale" : 1,
      "shoulderWidthMultiplier" : 0,
      "skeletonSize" : 0.5,
      "strokeThickness" : 0.5,
      "strokeThicknessJoints" : 2,
      "strokeThicknessLowerArms" : 4,
      "strokeThicknessLowerLegs" : 4,
      "strokeThicknessLowerTorso" : 5,
      "strokeThicknessMultiplier" : 0.5,
      "strokeThicknessUpperArms" : 4,
      "strokeThicknessUpperLegs" : 5,
      "strokeThicknessUpperTorso" : 5,
      "torsoColor" : "#000000",
      "torsoRotationAngle" : 0,
      "waistPositionX" : 300,
      "waistPositionY" : 360,
      "waistThicknessMultiplier" : 0,
      "waistTorsoAngle" : 0,
      "waistWidthMultiplier" : 0
    }
  },
  {
      "createdAt" : 1772665525.9815,
      "frameNumber" : 3,
      "id" : "0E9530A8-1209-4CA5-ACB2-4C3CD2F0F694",
      "name" : "Move",
      "objects" : [
      ],
      "pose" : {
        "figureOffsetX" : 0,
        "figureOffsetY" : 0,
        "figureScale" : 1,
        "footColor" : "#000000",
        "footSize" : 0.5,
        "fusiformLowerArms" : 0,
        "fusiformLowerLegs" : 0,
        "fusiformLowerTorso" : 0,
        "fusiformShoulders" : 0,
        "fusiformUpperArms" : 0,
        "fusiformUpperLegs" : 0,
        "fusiformUpperTorso" : 0,
        "handColor" : "#000000",
        "handSize" : 0.5,
        "headAngle" : 0,
        "headColor" : "#000000",
        "headRadiusMultiplier" : 1,
        "jointColor" : "#000000",
        "jointShapeSize" : 1,
        "leftArmColor" : "#000000",
        "leftElbowAngle" : -39,
        "leftFootAngle" : 61,
        "leftHandAngle" : 0,
        "leftHipAngle" : 0,
        "leftKneeAngle" : -226,
        "leftLegColor" : "#000000",
        "leftLowerArmColor" : "#000000",
        "leftLowerLegColor" : "#000000",
        "leftShoulderAngle" : -213,
        "leftUpperArmColor" : "#000000",
        "leftUpperLegColor" : "#000000",
        "midTorsoAngle" : 0,
        "neckLength" : 21,
        "neckWidth" : 3.3,
        "peakPositionLowerArms" : 0.1,
        "peakPositionLowerLegs" : 0.1,
        "peakPositionLowerTorso" : 0.1,
        "peakPositionUpperArms" : 0.1,
        "peakPositionUpperLegs" : 0.1,
        "peakPositionUpperTorso" : 0.1,
        "rightArmColor" : "#000000",
        "rightElbowAngle" : -32,
        "rightFootAngle" : 44,
        "rightHandAngle" : 0,
        "rightHipAngle" : 0,
        "rightKneeAngle" : 197,
        "rightLegColor" : "#000000",
        "rightLowerArmColor" : "#000000",
        "rightLowerLegColor" : "#000000",
        "rightShoulderAngle" : 220,
        "rightUpperArmColor" : "#000000",
        "rightUpperLegColor" : "#000000",
        "scale" : 1,
        "shoulderWidthMultiplier" : 0,
        "skeletonSize" : 0.5,
        "strokeThickness" : 0.5,
        "strokeThicknessJoints" : 2,
        "strokeThicknessLowerArms" : 4,
        "strokeThicknessLowerLegs" : 4,
        "strokeThicknessLowerTorso" : 5,
        "strokeThicknessMultiplier" : 0.5,
        "strokeThicknessUpperArms" : 4,
        "strokeThicknessUpperLegs" : 5,
        "strokeThicknessUpperTorso" : 5,
        "torsoColor" : "#000000",
        "torsoRotationAngle" : 0,
        "waistPositionX" : 300,
        "waistPositionY" : 360,
        "waistThicknessMultiplier" : 0,
        "waistTorsoAngle" : 0,
        "waistWidthMultiplier" : 0
      }
    },
  {
    "createdAt" : 1772665590.2314,
    "frameNumber" : 4,
    "id" : "1E42D252-C1CD-4D1F-955A-6A3E5B8D58F8",
    "name" : "Move",
    "objects" : [
    ],
    "pose" : {
      "figureOffsetX" : 0,
      "figureOffsetY" : 0,
      "figureScale" : 1,
      "footColor" : "#000000",
      "footSize" : 0.5,
      "fusiformLowerArms" : 0,
      "fusiformLowerLegs" : 0,
      "fusiformLowerTorso" : 0,
      "fusiformShoulders" : 0,
      "fusiformUpperArms" : 0,
      "fusiformUpperLegs" : 0,
      "fusiformUpperTorso" : 0,
      "handColor" : "#000000",
      "handSize" : 0.5,
      "headAngle" : 0,
      "headColor" : "#000000",
      "headRadiusMultiplier" : 1,
      "jointColor" : "#000000",
      "jointShapeSize" : 1,
      "leftArmColor" : "#000000",
      "leftElbowAngle" : -62,
      "leftFootAngle" : 17,
      "leftHandAngle" : 0,
      "leftHipAngle" : 0,
      "leftKneeAngle" : -226,
      "leftLegColor" : "#000000",
      "leftLowerArmColor" : "#000000",
      "leftLowerLegColor" : "#000000",
      "leftShoulderAngle" : -245,
      "leftUpperArmColor" : "#000000",
      "leftUpperLegColor" : "#000000",
      "midTorsoAngle" : 0,
      "neckLength" : 21,
      "neckWidth" : 3.3,
      "peakPositionLowerArms" : 0.1,
      "peakPositionLowerLegs" : 0.1,
      "peakPositionLowerTorso" : 0.1,
      "peakPositionUpperArms" : 0.1,
      "peakPositionUpperLegs" : 0.1,
      "peakPositionUpperTorso" : 0.1,
      "rightArmColor" : "#000000",
      "rightElbowAngle" : -47,
      "rightFootAngle" : 44,
      "rightHandAngle" : 0,
      "rightHipAngle" : 0,
      "rightKneeAngle" : 217,
      "rightLegColor" : "#000000",
      "rightLowerArmColor" : "#000000",
      "rightLowerLegColor" : "#000000",
      "rightShoulderAngle" : 265,
      "rightUpperArmColor" : "#000000",
      "rightUpperLegColor" : "#000000",
      "scale" : 1,
      "shoulderWidthMultiplier" : 0,
      "skeletonSize" : 0.5,
      "strokeThickness" : 0.5,
      "strokeThicknessJoints" : 2,
      "strokeThicknessLowerArms" : 4,
      "strokeThicknessLowerLegs" : 4,
      "strokeThicknessLowerTorso" : 5,
      "strokeThicknessMultiplier" : 0.5,
      "strokeThicknessUpperArms" : 4,
      "strokeThicknessUpperLegs" : 5,
      "strokeThicknessUpperTorso" : 5,
      "torsoColor" : "#000000",
      "torsoRotationAngle" : 0,
      "waistPositionX" : 300,
      "waistPositionY" : 360,
      "waistThicknessMultiplier" : 0,
      "waistTorsoAngle" : 0,
      "waistWidthMultiplier" : 0
    }
  },
  {
    "createdAt" : 1772649710.2342,
    "frameNumber" : 1,
    "id" : "BEC5C189-7F06-4A9F-A1D9-90E2D5EC505F",
    "name" : "Curls",
    "objects" : [
      {
        "id" : "05541887-C96A-4D1D-963D-B6C2E1FE58D0",
        "imageName" : "Dumbbell",
        "position" : {
          "x" : 162.7,
          "y" : 199.7
        },
        "rotation" : -0.14,
        "scale" : 0.5725
      },
      {
        "id" : "115E23DA-BFAE-4A54-BCBA-32082C031753",
        "imageName" : "Dumbbell",
        "position" : {
          "x" : 240,
          "y" : 198.3
        },
        "rotation" : 0.0867,
        "scale" : 0.5636
      }
    ],
    "pose" : {
      "figureOffsetX" : 0,
      "figureOffsetY" : 0,
      "figureScale" : 1,
      "footColor" : "#000000",
      "footSize" : 1,
      "fusiformLowerArms" : 2,
      "fusiformLowerLegs" : 2.48,
      "fusiformLowerTorso" : 1,
      "fusiformShoulders" : 1.52,
      "fusiformUpperArms" : 2.74,
      "fusiformUpperLegs" : 2.95,
      "fusiformUpperTorso" : 5.85,
      "handColor" : "#000000",
      "handSize" : 1,
      "headAngle" : 0,
      "headColor" : "#000000",
      "headRadiusMultiplier" : 1,
      "jointColor" : "#000000",
      "jointShapeSize" : 1,
      "leftArmColor" : "#000000",
      "leftElbowAngle" : -26,
      "leftFootAngle" : 0,
      "leftHandAngle" : 0,
      "leftHipAngle" : 0,
      "leftKneeAngle" : -166,
      "leftLegColor" : "#000000",
      "leftLowerArmColor" : "#000000",
      "leftLowerLegColor" : "#000000",
      "leftShoulderAngle" : -147,
      "leftUpperArmColor" : "#000000",
      "leftUpperLegColor" : "#000000",
      "midTorsoAngle" : 0,
      "neckLength" : 21,
      "neckWidth" : 8.5,
      "peakPositionLowerArms" : 0.3,
      "peakPositionLowerLegs" : 0.2,
      "peakPositionLowerTorso" : 0.5,
      "peakPositionUpperArms" : 0.47,
      "peakPositionUpperLegs" : 0.2,
      "peakPositionUpperTorso" : 0.1,
      "rightArmColor" : "#000000",
      "rightElbowAngle" : 26,
      "rightFootAngle" : 0,
      "rightHandAngle" : 0,
      "rightHipAngle" : 0,
      "rightKneeAngle" : 167,
      "rightLegColor" : "#000000",
      "rightLowerArmColor" : "#000000",
      "rightLowerLegColor" : "#000000",
      "rightShoulderAngle" : 147,
      "rightUpperArmColor" : "#000000",
      "rightUpperLegColor" : "#000000",
      "scale" : 1,
      "shoulderWidthMultiplier" : 0.52,
      "skeletonSize" : 4.18,
      "strokeThickness" : 1,
      "strokeThicknessJoints" : 2.5,
      "strokeThicknessLowerArms" : 3.5,
      "strokeThicknessLowerLegs" : 3.5,
      "strokeThicknessLowerTorso" : 4.5,
      "strokeThicknessMultiplier" : 1,
      "strokeThicknessUpperArms" : 4,
      "strokeThicknessUpperLegs" : 4.5,
      "strokeThicknessUpperTorso" : 5,
      "torsoColor" : "#000000",
      "torsoRotationAngle" : 0,
      "waistPositionX" : 300,
      "waistPositionY" : 360,
      "waistThicknessMultiplier" : 0.9,
      "waistTorsoAngle" : 0,
      "waistWidthMultiplier" : 0.26
    }
  }
]
